datslab/common/__init__.py
datslab/lr/__init__.py
datslab/mr/__init__.py
datslab/trends/__init__.py
dats_lab-0.0.50.dist-info/METADATA
dats_lab-0.0.50.dist-info/WHEEL
dats_lab-0.0.50.dist-info/top_level.txt
dats_lab-0.0.50.dist-info/RECORD
