Metadata-Version: 2.1
Name: dats-lab
Version: 0.0.50
Summary: Data Science Utilities & Helpers
Home-page: https://github.com/cbalkig/DataScienceUtils.git
Author: C. Balkı Gemirter
Author-email: cavide.balki@gmail.com
License: MIT
Platform: UNKNOWN
Requires-Dist: statsmodels (==0.13.1)
Requires-Dist: matplotlib (>=3.5.1)
Requires-Dist: pandas (>=1.3.5)
Requires-Dist: numpy (==1.21.4)
Requires-Dist: arviz (==0.11.4)
Requires-Dist: pymc3 (==3.11.4)
Requires-Dist: causalgraphicalmodels (>=0.0.4)
Requires-Dist: daft (>=0.1.2)
